[{"concurso": 1235, "data": "02/03/2026", "dezenas": null}, {"concurso": 1234, "data": "23/02/2026", "dezenas": null}, {"concurso": 1233, "data": "18/02/2026", "dezenas": null}, {"concurso": 1232, "data": "09/02/2026", "dezenas": null}, {"concurso": 1231, "data": "02/02/2026", "dezenas": null}, {"concurso": 1230, "data": "26/01/2026", "dezenas": null}, {"concurso": 1229, "data": "19/01/2026", "dezenas": null}, {"concurso": 1228, "data": "12/01/2026", "dezenas": null}, {"concurso": 1227, "data": "05/01/2026", "dezenas": null}, {"concurso": 1226, "data": "29/12/2025", "dezenas": null}, {"concurso": 1225, "data": "22/12/2025", "dezenas": null}, {"concurso": 1224, "data": "15/12/2025", "dezenas": null}, {"concurso": 1223, "data": "08/12/2025", "dezenas": null}, {"concurso": 1222, "data": "01/12/2025", "dezenas": null}, {"concurso": 1221, "data": "24/11/2025", "dezenas": null}, {"concurso": 1220, "data": "17/11/2025", "dezenas": null}, {"concurso": 1219, "data": "10/11/2025", "dezenas": null}, {"concurso": 1218, "data": "03/11/2025", "dezenas": null}, {"concurso": 1217, "data": "27/10/2025", "dezenas": null}, {"concurso": 1216, "data": "20/10/2025", "dezenas": null}]